.editorconfig
.gitignore
.gitlab-ci.yml
README.rst
publish.settings.sh
publish.sh
pyproject.toml
tsconfig.json
.idea/modules.xml
.idea/peek-plugin-chat.iml
.idea/inspectionProfiles/Project_Default.xml
.idea/inspectionProfiles/profiles_settings.xml
docs/conf.py
docs/index.rst
docs/rtfd_requirements.txt
docs/watch-docs.sh
docs/_static/.gitkeep
docs/api/index_api.rst
docs/overview/ChatPluginArchitectureDiagram.png
docs/overview/overview.rst
peek_plugin_chat/__init__.py
peek_plugin_chat/plugin_package.json
peek_plugin_chat.egg-info/PKG-INFO
peek_plugin_chat.egg-info/SOURCES.txt
peek_plugin_chat.egg-info/dependency_links.txt
peek_plugin_chat.egg-info/requires.txt
peek_plugin_chat.egg-info/top_level.txt
peek_plugin_chat/_private/PluginNames.py
peek_plugin_chat/_private/__init__.py
peek_plugin_chat/_private/alembic.ini
peek_plugin_chat/_private/admin-app/chat.module.ts
peek_plugin_chat/_private/admin-app/components/chat-page/chat-page.component.html
peek_plugin_chat/_private/admin-app/components/chat-page/chat-page.component.scss
peek_plugin_chat/_private/admin-app/components/chat-page/chat-page.component.ts
peek_plugin_chat/_private/alembic/__init__.py
peek_plugin_chat/_private/alembic/env.py
peek_plugin_chat/_private/alembic/script.py.mako
peek_plugin_chat/_private/alembic/versions/5288d02e94e4_initial_schema.py
peek_plugin_chat/_private/alembic/versions/52f3163b45de_added_read_payload_constraint.py
peek_plugin_chat/_private/alembic/versions/9b0976dcfd53_truncate_chats.py
peek_plugin_chat/_private/alembic/versions/__init__.py
peek_plugin_chat/_private/alembic/versions/a4d6b26d39b7_timezone_aware.py
peek_plugin_chat/_private/client/ClientEntryHook.py
peek_plugin_chat/_private/client/DeviceTupleDataObservableProxy.py
peek_plugin_chat/_private/client/DeviceTupleProcessorActionProxy.py
peek_plugin_chat/_private/client/__init__.py
peek_plugin_chat/_private/mobile-app/chat.module.ts
peek_plugin_chat/_private/mobile-app/chat.routes.ts
peek_plugin_chat/_private/mobile-app/chat-list/chat-list.component.mweb.html
peek_plugin_chat/_private/mobile-app/chat-list/chat-list.component.ts
peek_plugin_chat/_private/mobile-app/chat-list/new-chat/new-chat.component.mweb.html
