Metadata-Version: 2.4
Name: peek-plugin-chat
Version: 5.0.4
Summary: Peek Plugin - Chat - Chat between users in the Peek platform
Author-email: Synerty <contact@synerty.com>
Project-URL: Homepage, https://github.com/Synerty/peek-plugin-chat
Keywords: Peek,Python,Platform,synerty
Requires-Dist: peek-plugin-base==5.0.4
